or_pcd/__init__.py
or_pcd/test.py
or_pcd/Aligner/Aligner.py
or_pcd/Aligner/__init__.py
or_pcd/Optimizer/__init__.py
or_pcd/Optimizer/fastGlobalOptimizer.py
or_pcd/Optimizer/generalizedICP.py
or_pcd/Optimizer/iOptimizer.py
or_pcd/Preprocessor/__init__.py
or_pcd/Preprocessor/iProcessBlock.py
or_pcd/Preprocessor/preprocessor.py
or_pcd/Preprocessor/Downsamplers/__init__.py
or_pcd/Preprocessor/Downsamplers/farthestDownsampler.py
or_pcd/Preprocessor/Downsamplers/randomDownsampler.py
or_pcd/Preprocessor/Downsamplers/voxelDownsampler.py
or_pcd/Preprocessor/Outliers/__init__.py
or_pcd/Preprocessor/Outliers/sor.py
or_pcd/Preprocessor/Scalers/BaseScaler.py
or_pcd/Preprocessor/Scalers/__init__.py
or_pcd/Preprocessor/Scalers/radiusScaler.py
or_pcd/Visualizer/Visualizer.py
or_pcd/Visualizer/__init__.py
or_pcd/data/ArmadilloBack.conf
or_pcd/data/ArmadilloBack_0.ply
or_pcd/data/ArmadilloBack_180.ply
or_pcd/data/ArmadilloBack_30.ply
or_pcd/data/ArmadilloBack_330.ply
or_pcd/data/ArmadilloBack_60.ply
or_pcd/data/ArmadilloOnFace.conf
or_pcd/data/ArmadilloOnHeadMultiple_150.ply
or_pcd/data/ArmadilloOnHeadMultiple_240.ply
or_pcd/data/ArmadilloOnface_270.ply
or_pcd/data/__init__.py
or_pcd/utils/__init__.py
or_pcd/utils/constants.py
or_pcd/utils/create_cloud.py
or_pcd/utils/logger_factory.py
or_pcd-0.0.1b7.dist-info/LICENSE
or_pcd-0.0.1b7.dist-info/METADATA
or_pcd-0.0.1b7.dist-info/WHEEL
or_pcd-0.0.1b7.dist-info/top_level.txt
or_pcd-0.0.1b7.dist-info/RECORD
