Metadata-Version: 2.1
Name: or-pcd
Version: 0.0.1b7
Summary: A python package to perform pointcloud registration with scale differences using a two-block optimization approach
Home-page: https://github.com/dpolimeni/Multi-scale-pointcloud-registration
Author: Diego Polimeni and Alessandro Pannone
Author-email: a.pannone1798@gmail.com
License: MIT
Classifier: License :: OSI Approved :: MIT License
Classifier: Programming Language :: Python :: 3.10
Classifier: Operating System :: OS Independent
Requires-Python: >=3.11
License-File: LICENSE
Requires-Dist: numpy ==1.26.4
Requires-Dist: scikit-learn ==1.4.1.post1
Requires-Dist: open3d ==0.18.0
Provides-Extra: dev
Requires-Dist: pytest >=7.0 ; extra == 'dev'
Requires-Dist: twine >=4.0.2 ; extra == 'dev'
